{"longInfo":"Passport required.\n- Passports and/or passport replacing documents must be valid\n  on arrival.\n\nVISA NOT REQUIRED.\n\nAdditional Information:\n- Visitors are required to hold documents required for their\n  next destination. (SEE NOTE 54543)\n    NOTE 54543: Not applicable to nationals of EEA Member\n   States  and Switzerland.\nWarning:\n- Visitors not holding return/onward tickets  co\n  uld be refused entry. (SEE NOTE 54543) \n    NOTE 54543: Not applicable to nationals of EEA Member\n   States  and Switzerland","vaccination":"Vaccinations not required.\n\nRecommended:\n- Malaria prophylaxis: malaria risk, mainly due to P.\n  falciparum, exists throughout the year. Recommended\n  prevention: C.","Type":"NotRequired","Schengen":"Unknown","USA":"Unknown","target":"MYT","shortInfo":null,"alias":{"general":"green","schengen":"red","usa":"red"}}