{"longInfo":"Passport required.\n- Passports must be valid for at least 6 months from date of\n  arrival. \n\nVisa Issuance:\nVisa required, except for Nationals of Burkina Faso can obtain\na single entry visa on arrival, for a max. stay of 30 days,\nprovided passport contains 1 unused visa page. Fee: USD 30.-\n(payable in USD only).\nVisa required, except for Nationals of Burkina Faso can obtain\na multiple entry visa on arrival, for a max. stay between 30\nand 90 days, provided:  \nAdditional Information:\n- Nationals of Burkina Faso may extend their stay to a total\n  cumulative stay of 90 days by submitting their application\n  to the Immigration Department. Fee: USD 35.- for up to 30\n  days; USD 75.- for between 30 and 60 days. \n- Visitors are required to hold proof of sufficient funds to\n  cover their stay (USD 150.- per day), proof of hotel\n  accommodations arrangements and documents required for their\n  next destination.\n- Those who have overstayed their visa may be subject to\n  fines.\nWarning:\n- Visitors not holding return/onward tickets could be refused\n  entry","vaccination":"Vaccination against yellow fever required if arriving within 6\ndays after leaving or transiting countries with risk of yellow\nfever transmission For details, click here.\n\nExempt from Yellow Fever vaccination:\n- Children under 1 year of age.\n- Passengers transiting countries with risk of yellow fever\n  transmission provided not leaving the transit areas.\nRecommended:\n- Malaria prophylaxis: malaria risk, mainly due to P.\n  falciparum, exists throughout the year in the whole country.\n  Recommended prevention: C.","Type":"OnArrival","Schengen":"Unknown","USA":"Unknown","target":"TLS","shortInfo":null,"alias":{"general":"yellow","schengen":"red","usa":"red"}}