{"longInfo":"Passport required.\n- Passports and/or passport replacing documents must be valid\n  on arrival.\n\nVisa required, except for A max. stay of 30 days for nationals\nof Tonga. \nAdditional Information:\n- Visitors are required to hold proof of sufficient funds to\n  cover their stay and documents required for their next\n  destination.\n- Persons intending to stay longer than 90 days, must\n   \n- Extension of stay possible for a total stay of 90 days to\n  nationals of Tonga\nWarning:\n- Visitors not holding return/onward tickets or sufficient\n  funds to purchase a ticket, could be refused entry","vaccination":"Vaccination against yellow fever required if arriving within 6\ndays after leaving or transiting countries with risk of yellow\nfever transmission For details, click here.\n\nExempt from Yellow Fever vaccination:\n- Passengers transiting countries with risk of yellow fever\n  transmission provided not leaving the transit areas.\nRecommended:\n- Malaria prophylaxis: malaria risk, mainly due to P.\n  falciparum, exists throughout the year in all low veld areas\n  (mainly Big Bend, Mhlume, Simunye and Tshaneni). Risk is\n  highest from November to May. Recommended prevention in risk\n  areas: C.","Type":"OnArrival","Schengen":"Unknown","USA":"Unknown","target":"SWZ","shortInfo":null,"alias":{"general":"yellow","schengen":"red","usa":"red"}}